sapicore/__init__.py
sapicore/data/__init__.py
sapicore/data/external/__init__.py
sapicore/data/external/drift.py
sapicore/data/sampling/__init__.py
sapicore/engine/__init__.py
sapicore/engine/component/__init__.py
sapicore/engine/ensemble/__init__.py
sapicore/engine/ensemble/analog.py
sapicore/engine/ensemble/spiking.py
sapicore/engine/network/__init__.py
sapicore/engine/neuron/__init__.py
sapicore/engine/neuron/analog/__init__.py
sapicore/engine/neuron/analog/oscillator.py
sapicore/engine/neuron/spiking/IZ.py
sapicore/engine/neuron/spiking/LIF.py
sapicore/engine/neuron/spiking/__init__.py
sapicore/engine/synapse/STDP.py
sapicore/engine/synapse/__init__.py
sapicore/model/__init__.py
sapicore/pipeline/__init__.py
sapicore/pipeline/simple.py
sapicore/tests/__init__.py
sapicore/tests/data/__init__.py
sapicore/tests/data/test_data.py
sapicore/tests/data/test_drift.py
sapicore/tests/engine/__init__.py
sapicore/tests/engine/ensemble/__init__.py
sapicore/tests/engine/ensemble/test_ensemble.py
sapicore/tests/engine/network/__init__.py
sapicore/tests/engine/network/test_network.py
sapicore/tests/engine/neuron/__init__.py
sapicore/tests/engine/neuron/test_neuron.py
sapicore/tests/engine/synapse/__init__.py
sapicore/tests/engine/synapse/test_synapse.py
sapicore/tests/pipeline/__init__.py
sapicore/tests/scripts/__init__.py
sapicore/tests/scripts/purge_logs.py
sapicore/tests/scripts/run_tests.py
sapicore/tests/scripts/start_tb.py
sapicore/tests/utils/__init__.py
sapicore/tests/utils/test_integration.py
sapicore/utils/__init__.py
sapicore/utils/constants.py
sapicore/utils/integration.py
sapicore/utils/io.py
sapicore/utils/plotting.py
sapicore/utils/seed.py
sapicore/utils/signals.py
sapicore/utils/sweep.py
sapicore/utils/tensorboard.py
sapicore/utils/loggable/__init__.py
sapicore-0.4.1.dist-info/METADATA
sapicore-0.4.1.dist-info/WHEEL
sapicore-0.4.1.dist-info/top_level.txt
sapicore-0.4.1.dist-info/RECORD
