Metadata-Version: 2.1
Name: sapicore
Version: 0.4.1
Summary: A framework for spiking neural network modeling. 
Home-page: https://github.com/cplab/sapicore
Author: Roy Moyal, Matthew Einhorn, Ayon Borthakur, Thomas Cleland
Author-email: rm875@cornell.edu, me263@cornell.edu, ayon.borthakur@ai.iith.ac.in, tac29@cornell.edu
Classifier: Development Status :: 4 - Beta
Classifier: Programming Language :: Python :: 3.10
Classifier: Programming Language :: Python :: 3.11
Requires-Dist: h5py
Requires-Dist: numpy
Requires-Dist: scipy
Requires-Dist: pandas
Requires-Dist: torch
Requires-Dist: tensorboard
Requires-Dist: networkx
Requires-Dist: scikit-learn
Requires-Dist: matplotlib
Requires-Dist: PyYAML
Requires-Dist: nixio
Requires-Dist: dill
Requires-Dist: natsort
Requires-Dist: alive_progress
Requires-Dist: tree-config
Requires-Dist: pytest
Requires-Dist: setuptools
Provides-Extra: dev
Requires-Dist: coverage; extra == "dev"
Requires-Dist: flake8; extra == "dev"
Requires-Dist: sphinx<7.0.0; extra == "dev"
Requires-Dist: sphinx-rtd-theme; extra == "dev"
Requires-Dist: m2r2; extra == "dev"
